Bigquery_dependency_email_trigger/__init__.py
Bigquery_dependency_email_trigger/main.py
Bigquery_dependency_email_trigger-0.1.dist-info/METADATA
Bigquery_dependency_email_trigger-0.1.dist-info/WHEEL
Bigquery_dependency_email_trigger-0.1.dist-info/entry_points.txt
Bigquery_dependency_email_trigger-0.1.dist-info/top_level.txt
Bigquery_dependency_email_trigger-0.1.dist-info/RECORD
