Metadata-Version: 2.1
Name: Bigquery-dependency-email-trigger
Version: 0.1
